{"_format":"","paths":{"artifacts":"out","build_infos":"out/build-info","sources":"src","tests":"test","scripts":"script","libraries":["node_modules"]},"files":{"node_modules/drosera-contracts/src/interfaces/ITrap.sol":{"lastModificationDate":1773940520650,"contentHash":"ee77a470d9a64b35","interfaceReprHash":null,"sourceName":"node_modules/drosera-contracts/src/interfaces/ITrap.sol","imports":[],"versionRequirement":"^0.8.12","artifacts":{"ITrap":{"0.8.33":{"default":{"path":"interfaces/ITrap.sol/ITrap.json","build_id":"e748f7338fd29765"}}}},"seenByCompiler":true},"node_modules/forge-std/src/Base.sol":{"lastModificationDate":1773940523814,"contentHash":"6f3a6f93872b8615","interfaceReprHash":null,"sourceName":"node_modules/forge-std/src/Base.sol","imports":["node_modules/forge-std/src/StdStorage.sol","node_modules/forge-std/src/Vm.sol"],"versionRequirement":">=0.6.2, <0.9.0","artifacts":{"CommonBase":{"0.8.33":{"default":{"path":"Base.sol/CommonBase.json","build_id":"e748f7338fd29765"}}},"ScriptBase":{"0.8.33":{"default":{"path":"Base.sol/ScriptBase.json","build_id":"e748f7338fd29765"}}},"TestBase":{"0.8.33":{"default":{"path":"Base.sol/TestBase.json","build_id":"e748f7338fd29765"}}}},"seenByCompiler":true},"node_modules/forge-std/src/StdAssertions.sol":{"lastModificationDate":1773940523814,"contentHash":"f4f836e440ec91ad","interfaceReprHash":null,"sourceName":"node_modules/forge-std/src/StdAssertions.sol","imports":["node_modules/forge-std/src/Vm.sol"],"versionRequirement":">=0.6.2, <0.9.0","artifacts":{"StdAssertions":{"0.8.33":{"default":{"path":"StdAssertions.sol/StdAssertions.json","build_id":"e748f7338fd29765"}}}},"seenByCompiler":true},"node_modules/forge-std/src/StdChains.sol":{"lastModificationDate":1773940523814,"contentHash":"b6b2b3ed900470d7","interfaceReprHash":null,"sourceName":"node_modules/forge-std/src/StdChains.sol","imports":["node_modules/forge-std/src/Vm.sol"],"versionRequirement":">=0.6.2, <0.9.0","artifacts":{"StdChains":{"0.8.33":{"default":{"path":"StdChains.sol/StdChains.json","build_id":"e748f7338fd29765"}}}},"seenByCompiler":true},"node_modules/forge-std/src/StdCheats.sol":{"lastModificationDate":1773940523814,"contentHash":"dad445e91b31954d","interfaceReprHash":null,"sourceName":"node_modules/forge-std/src/StdCheats.sol","imports":["node_modules/forge-std/src/StdStorage.sol","node_modules/forge-std/src/Vm.sol","node_modules/forge-std/src/console2.sol"],"versionRequirement":">=0.6.2, <0.9.0","artifacts":{"StdCheats":{"0.8.33":{"default":{"path":"StdCheats.sol/StdCheats.json","build_id":"e748f7338fd29765"}}},"StdCheatsSafe":{"0.8.33":{"default":{"path":"StdCheats.sol/StdCheatsSafe.json","build_id":"e748f7338fd29765"}}}},"seenByCompiler":true},"node_modules/forge-std/src/StdError.sol":{"lastModificationDate":1773940523814,"contentHash":"a1a86c7115e2cdf3","interfaceReprHash":null,"sourceName":"node_modules/forge-std/src/StdError.sol","imports":[],"versionRequirement":">=0.6.2, <0.9.0","artifacts":{"stdError":{"0.8.33":{"default":{"path":"StdError.sol/stdError.json","build_id":"e748f7338fd29765"}}}},"seenByCompiler":true},"node_modules/forge-std/src/StdInvariant.sol":{"lastModificationDate":1773940523814,"contentHash":"5ce1c5e7171c2f60","interfaceReprHash":null,"sourceName":"node_modules/forge-std/src/StdInvariant.sol","imports":[],"versionRequirement":">=0.6.2, <0.9.0","artifacts":{"StdInvariant":{"0.8.33":{"default":{"path":"StdInvariant.sol/StdInvariant.json","build_id":"e748f7338fd29765"}}}},"seenByCompiler":true},"node_modules/forge-std/src/StdJson.sol":{"lastModificationDate":1773940523814,"contentHash":"6af7fc1959d7e5a6","interfaceReprHash":null,"sourceName":"node_modules/forge-std/src/StdJson.sol","imports":["node_modules/forge-std/src/Vm.sol"],"versionRequirement":">=0.6.0, <0.9.0","artifacts":{"stdJson":{"0.8.33":{"default":{"path":"StdJson.sol/stdJson.json","build_id":"e748f7338fd29765"}}}},"seenByCompiler":true},"node_modules/forge-std/src/StdMath.sol":{"lastModificationDate":1773940523814,"contentHash":"72584abebada1e7a","interfaceReprHash":null,"sourceName":"node_modules/forge-std/src/StdMath.sol","imports":[],"versionRequirement":">=0.6.2, <0.9.0","artifacts":{"stdMath":{"0.8.33":{"default":{"path":"StdMath.sol/stdMath.json","build_id":"e748f7338fd29765"}}}},"seenByCompiler":true},"node_modules/forge-std/src/StdStorage.sol":{"lastModificationDate":1773940523814,"contentHash":"d9f44b1d7791cbd0","interfaceReprHash":null,"sourceName":"node_modules/forge-std/src/StdStorage.sol","imports":["node_modules/forge-std/src/Vm.sol"],"versionRequirement":">=0.6.2, <0.9.0","artifacts":{"stdStorage":{"0.8.33":{"default":{"path":"StdStorage.sol/stdStorage.json","build_id":"e748f7338fd29765"}}},"stdStorageSafe":{"0.8.33":{"default":{"path":"StdStorage.sol/stdStorageSafe.json","build_id":"e748f7338fd29765"}}}},"seenByCompiler":true},"node_modules/forge-std/src/StdStyle.sol":{"lastModificationDate":1773940523818,"contentHash":"ee166ef95092736e","interfaceReprHash":null,"sourceName":"node_modules/forge-std/src/StdStyle.sol","imports":["node_modules/forge-std/src/Vm.sol"],"versionRequirement":">=0.4.22, <0.9.0","artifacts":{"StdStyle":{"0.8.33":{"default":{"path":"StdStyle.sol/StdStyle.json","build_id":"e748f7338fd29765"}}}},"seenByCompiler":true},"node_modules/forge-std/src/StdToml.sol":{"lastModificationDate":1773940523818,"contentHash":"edbc8bff3ba32b22","interfaceReprHash":null,"sourceName":"node_modules/forge-std/src/StdToml.sol","imports":["node_modules/forge-std/src/Vm.sol"],"versionRequirement":">=0.6.0, <0.9.0","artifacts":{"stdToml":{"0.8.33":{"default":{"path":"StdToml.sol/stdToml.json","build_id":"e748f7338fd29765"}}}},"seenByCompiler":true},"node_modules/forge-std/src/StdUtils.sol":{"lastModificationDate":1773940523818,"contentHash":"5f6ed7eac4d4e2a9","interfaceReprHash":null,"sourceName":"node_modules/forge-std/src/StdUtils.sol","imports":["node_modules/forge-std/src/Vm.sol","node_modules/forge-std/src/interfaces/IERC165.sol","node_modules/forge-std/src/interfaces/IERC20.sol","node_modules/forge-std/src/interfaces/IERC721.sol","node_modules/forge-std/src/interfaces/IMulticall3.sol","node_modules/forge-std/src/mocks/MockERC20.sol","node_modules/forge-std/src/mocks/MockERC721.sol"],"versionRequirement":">=0.6.2, <0.9.0","artifacts":{"StdUtils":{"0.8.33":{"default":{"path":"StdUtils.sol/StdUtils.json","build_id":"e748f7338fd29765"}}}},"seenByCompiler":true},"node_modules/forge-std/src/Test.sol":{"lastModificationDate":1773940523818,"contentHash":"a18f53966ac7b768","interfaceReprHash":null,"sourceName":"node_modules/forge-std/src/Test.sol","imports":["node_modules/forge-std/src/Base.sol","node_modules/forge-std/src/StdAssertions.sol","node_modules/forge-std/src/StdChains.sol","node_modules/forge-std/src/StdCheats.sol","node_modules/forge-std/src/StdError.sol","node_modules/forge-std/src/StdInvariant.sol","node_modules/forge-std/src/StdJson.sol","node_modules/forge-std/src/StdMath.sol","node_modules/forge-std/src/StdStorage.sol","node_modules/forge-std/src/StdStyle.sol","node_modules/forge-std/src/StdToml.sol","node_modules/forge-std/src/StdUtils.sol","node_modules/forge-std/src/Vm.sol","node_modules/forge-std/src/console.sol","node_modules/forge-std/src/console2.sol","node_modules/forge-std/src/interfaces/IERC165.sol","node_modules/forge-std/src/interfaces/IERC20.sol","node_modules/forge-std/src/interfaces/IERC721.sol","node_modules/forge-std/src/interfaces/IMulticall3.sol","node_modules/forge-std/src/mocks/MockERC20.sol","node_modules/forge-std/src/mocks/MockERC721.sol","node_modules/forge-std/src/safeconsole.sol"],"versionRequirement":">=0.6.2, <0.9.0","artifacts":{"Test":{"0.8.33":{"default":{"path":"Test.sol/Test.json","build_id":"e748f7338fd29765"}}}},"seenByCompiler":true},"node_modules/forge-std/src/Vm.sol":{"lastModificationDate":1773940523818,"contentHash":"f30d5171619f96ac","interfaceReprHash":null,"sourceName":"node_modules/forge-std/src/Vm.sol","imports":[],"versionRequirement":">=0.6.2, <0.9.0","artifacts":{"Vm":{"0.8.33":{"default":{"path":"Vm.sol/Vm.json","build_id":"e748f7338fd29765"}}},"VmSafe":{"0.8.33":{"default":{"path":"Vm.sol/VmSafe.json","build_id":"e748f7338fd29765"}}}},"seenByCompiler":true},"node_modules/forge-std/src/console.sol":{"lastModificationDate":1773940523818,"contentHash":"312dcca23be79f11","interfaceReprHash":null,"sourceName":"node_modules/forge-std/src/console.sol","imports":[],"versionRequirement":">=0.4.22, <0.9.0","artifacts":{"console":{"0.8.33":{"default":{"path":"console.sol/console.json","build_id":"e748f7338fd29765"}}}},"seenByCompiler":true},"node_modules/forge-std/src/console2.sol":{"lastModificationDate":1773940523818,"contentHash":"c3b5bec319ec7509","interfaceReprHash":null,"sourceName":"node_modules/forge-std/src/console2.sol","imports":[],"versionRequirement":">=0.4.22, <0.9.0","artifacts":{"console2":{"0.8.33":{"default":{"path":"console2.sol/console2.json","build_id":"e748f7338fd29765"}}}},"seenByCompiler":true},"node_modules/forge-std/src/interfaces/IERC165.sol":{"lastModificationDate":1773940523822,"contentHash":"32018de4ee034f09","interfaceReprHash":null,"sourceName":"node_modules/forge-std/src/interfaces/IERC165.sol","imports":[],"versionRequirement":">=0.6.2","artifacts":{"IERC165":{"0.8.33":{"default":{"path":"IERC165.sol/IERC165.json","build_id":"e748f7338fd29765"}}}},"seenByCompiler":true},"node_modules/forge-std/src/interfaces/IERC20.sol":{"lastModificationDate":1773940523822,"contentHash":"776150aa4a93e925","interfaceReprHash":null,"sourceName":"node_modules/forge-std/src/interfaces/IERC20.sol","imports":[],"versionRequirement":">=0.6.2","artifacts":{"IERC20":{"0.8.33":{"default":{"path":"IERC20.sol/IERC20.json","build_id":"e748f7338fd29765"}}}},"seenByCompiler":true},"node_modules/forge-std/src/interfaces/IERC721.sol":{"lastModificationDate":1773940523822,"contentHash":"a4a12cc0c6148262","interfaceReprHash":null,"sourceName":"node_modules/forge-std/src/interfaces/IERC721.sol","imports":["node_modules/forge-std/src/interfaces/IERC165.sol"],"versionRequirement":">=0.6.2","artifacts":{"IERC721":{"0.8.33":{"default":{"path":"IERC721.sol/IERC721.json","build_id":"e748f7338fd29765"}}},"IERC721Enumerable":{"0.8.33":{"default":{"path":"IERC721.sol/IERC721Enumerable.json","build_id":"e748f7338fd29765"}}},"IERC721Metadata":{"0.8.33":{"default":{"path":"IERC721.sol/IERC721Metadata.json","build_id":"e748f7338fd29765"}}},"IERC721TokenReceiver":{"0.8.33":{"default":{"path":"IERC721.sol/IERC721TokenReceiver.json","build_id":"e748f7338fd29765"}}}},"seenByCompiler":true},"node_modules/forge-std/src/interfaces/IMulticall3.sol":{"lastModificationDate":1773940523822,"contentHash":"b680a332ebf10901","interfaceReprHash":null,"sourceName":"node_modules/forge-std/src/interfaces/IMulticall3.sol","imports":[],"versionRequirement":">=0.6.2, <0.9.0","artifacts":{"IMulticall3":{"0.8.33":{"default":{"path":"IMulticall3.sol/IMulticall3.json","build_id":"e748f7338fd29765"}}}},"seenByCompiler":true},"node_modules/forge-std/src/mocks/MockERC20.sol":{"lastModificationDate":1773940523822,"contentHash":"91ed77cb7e32725c","interfaceReprHash":null,"sourceName":"node_modules/forge-std/src/mocks/MockERC20.sol","imports":["node_modules/forge-std/src/interfaces/IERC20.sol"],"versionRequirement":">=0.6.2, <0.9.0","artifacts":{"MockERC20":{"0.8.33":{"default":{"path":"MockERC20.sol/MockERC20.json","build_id":"e748f7338fd29765"}}}},"seenByCompiler":true},"node_modules/forge-std/src/mocks/MockERC721.sol":{"lastModificationDate":1773940523822,"contentHash":"4fbc44c2e81da37f","interfaceReprHash":null,"sourceName":"node_modules/forge-std/src/mocks/MockERC721.sol","imports":["node_modules/forge-std/src/interfaces/IERC165.sol","node_modules/forge-std/src/interfaces/IERC721.sol"],"versionRequirement":">=0.6.2, <0.9.0","artifacts":{"IERC721TokenReceiver":{"0.8.33":{"default":{"path":"MockERC721.sol/IERC721TokenReceiver.json","build_id":"e748f7338fd29765"}}},"MockERC721":{"0.8.33":{"default":{"path":"MockERC721.sol/MockERC721.json","build_id":"e748f7338fd29765"}}}},"seenByCompiler":true},"node_modules/forge-std/src/safeconsole.sol":{"lastModificationDate":1773940523822,"contentHash":"2c9ce919dbbf10eb","interfaceReprHash":null,"sourceName":"node_modules/forge-std/src/safeconsole.sol","imports":[],"versionRequirement":">=0.6.2, <0.9.0","artifacts":{"safeconsole":{"0.8.33":{"default":{"path":"safeconsole.sol/safeconsole.json","build_id":"e748f7338fd29765"}}}},"seenByCompiler":true},"src/BybitSafeTrapV2.sol":{"lastModificationDate":1776618553460,"contentHash":"beab8c97f42dc802","interfaceReprHash":null,"sourceName":"src/BybitSafeTrapV2.sol","imports":["src/interfaces/ITrap.sol"],"versionRequirement":"^0.8.20","artifacts":{"BybitSafeTrapV2":{"0.8.33":{"default":{"path":"BybitSafeTrapV2.sol/BybitSafeTrapV2.json","build_id":"e748f7338fd29765"}}},"IERC20Like":{"0.8.33":{"default":{"path":"BybitSafeTrapV2.sol/IERC20Like.json","build_id":"e748f7338fd29765"}}},"ISafeLike":{"0.8.33":{"default":{"path":"BybitSafeTrapV2.sol/ISafeLike.json","build_id":"e748f7338fd29765"}}}},"seenByCompiler":true},"src/SafeGuardResponderV2.sol":{"lastModificationDate":1776618482488,"contentHash":"38945d07625c9369","interfaceReprHash":null,"sourceName":"src/SafeGuardResponderV2.sol","imports":["src/SafeGuardianRegistry.sol"],"versionRequirement":"^0.8.20","artifacts":{"SafeGuardResponderV2":{"0.8.33":{"default":{"path":"SafeGuardResponderV2.sol/SafeGuardResponderV2.json","build_id":"e748f7338fd29765"}}}},"seenByCompiler":true},"src/SafeGuardianRegistry.sol":{"lastModificationDate":1776618386164,"contentHash":"65f31668d43e8307","interfaceReprHash":null,"sourceName":"src/SafeGuardianRegistry.sol","imports":[],"versionRequirement":"^0.8.20","artifacts":{"IEmergencyActionTarget":{"0.8.33":{"default":{"path":"SafeGuardianRegistry.sol/IEmergencyActionTarget.json","build_id":"e748f7338fd29765"}}},"SafeGuardianRegistry":{"0.8.33":{"default":{"path":"SafeGuardianRegistry.sol/SafeGuardianRegistry.json","build_id":"e748f7338fd29765"}}}},"seenByCompiler":true},"src/interfaces/ITrap.sol":{"lastModificationDate":1776618373400,"contentHash":"4ddb47cc13edc714","interfaceReprHash":null,"sourceName":"src/interfaces/ITrap.sol","imports":[],"versionRequirement":"^0.8.20","artifacts":{"ITrap":{"0.8.33":{"default":{"path":"ITrap.sol/ITrap.json","build_id":"e748f7338fd29765"}}}},"seenByCompiler":true},"src/mocks/MockGuardianTarget.sol":{"lastModificationDate":1776618491016,"contentHash":"0b187c39f9aed7c2","interfaceReprHash":null,"sourceName":"src/mocks/MockGuardianTarget.sol","imports":["src/SafeGuardianRegistry.sol"],"versionRequirement":"^0.8.20","artifacts":{"MockGuardianTarget":{"0.8.33":{"default":{"path":"MockGuardianTarget.sol/MockGuardianTarget.json","build_id":"e748f7338fd29765"}}}},"seenByCompiler":true},"src/v1/BybitSafeTrap.sol":{"lastModificationDate":1776270884558,"contentHash":"afad33b68455957c","interfaceReprHash":null,"sourceName":"src/v1/BybitSafeTrap.sol","imports":["node_modules/drosera-contracts/src/interfaces/ITrap.sol"],"versionRequirement":"^0.8.20","artifacts":{"BybitSafeTrap":{"0.8.33":{"default":{"path":"BybitSafeTrap.sol/BybitSafeTrap.json","build_id":"0525ed644d1bda42"}}},"IERC20":{"0.8.33":{"default":{"path":"BybitSafeTrap.sol/IERC20.json","build_id":"0525ed644d1bda42"}}},"ISafe":{"0.8.33":{"default":{"path":"BybitSafeTrap.sol/ISafe.json","build_id":"0525ed644d1bda42"}}}},"seenByCompiler":true},"src/v1/SafeGuardResponder.sol":{"lastModificationDate":1776172297042,"contentHash":"c7424a7ab1d64883","interfaceReprHash":null,"sourceName":"src/v1/SafeGuardResponder.sol","imports":[],"versionRequirement":"^0.8.20","artifacts":{"SafeGuardResponder":{"0.8.33":{"default":{"path":"SafeGuardResponder.sol/SafeGuardResponder.json","build_id":"0525ed644d1bda42"}}}},"seenByCompiler":true},"test/BybitSafeTrapV2.t.sol":{"lastModificationDate":1776618967000,"contentHash":"6796b67bf6ec1a2e","interfaceReprHash":null,"sourceName":"test/BybitSafeTrapV2.t.sol","imports":["node_modules/forge-std/src/Base.sol","node_modules/forge-std/src/StdAssertions.sol","node_modules/forge-std/src/StdChains.sol","node_modules/forge-std/src/StdCheats.sol","node_modules/forge-std/src/StdError.sol","node_modules/forge-std/src/StdInvariant.sol","node_modules/forge-std/src/StdJson.sol","node_modules/forge-std/src/StdMath.sol","node_modules/forge-std/src/StdStorage.sol","node_modules/forge-std/src/StdStyle.sol","node_modules/forge-std/src/StdToml.sol","node_modules/forge-std/src/StdUtils.sol","node_modules/forge-std/src/Test.sol","node_modules/forge-std/src/Vm.sol","node_modules/forge-std/src/console.sol","node_modules/forge-std/src/console2.sol","node_modules/forge-std/src/interfaces/IERC165.sol","node_modules/forge-std/src/interfaces/IERC20.sol","node_modules/forge-std/src/interfaces/IERC721.sol","node_modules/forge-std/src/interfaces/IMulticall3.sol","node_modules/forge-std/src/mocks/MockERC20.sol","node_modules/forge-std/src/mocks/MockERC721.sol","node_modules/forge-std/src/safeconsole.sol","src/BybitSafeTrapV2.sol","src/SafeGuardResponderV2.sol","src/SafeGuardianRegistry.sol","src/interfaces/ITrap.sol","src/mocks/MockGuardianTarget.sol"],"versionRequirement":"^0.8.20","artifacts":{"BybitSafeTrapV2Test":{"0.8.33":{"default":{"path":"BybitSafeTrapV2.t.sol/BybitSafeTrapV2Test.json","build_id":"0fe6f21af39541ec"}}},"ISafeV2":{"0.8.33":{"default":{"path":"BybitSafeTrapV2.t.sol/ISafeV2.json","build_id":"0fe6f21af39541ec"}}},"SafeGuardResponderV2Test":{"0.8.33":{"default":{"path":"BybitSafeTrapV2.t.sol/SafeGuardResponderV2Test.json","build_id":"0fe6f21af39541ec"}}}},"seenByCompiler":true},"test/v1/BybitSafeTrap.t.sol":{"lastModificationDate":1776619193004,"contentHash":"4156abc4bb3a3221","interfaceReprHash":null,"sourceName":"test/v1/BybitSafeTrap.t.sol","imports":["node_modules/drosera-contracts/src/interfaces/ITrap.sol","node_modules/forge-std/src/Base.sol","node_modules/forge-std/src/StdAssertions.sol","node_modules/forge-std/src/StdChains.sol","node_modules/forge-std/src/StdCheats.sol","node_modules/forge-std/src/StdError.sol","node_modules/forge-std/src/StdInvariant.sol","node_modules/forge-std/src/StdJson.sol","node_modules/forge-std/src/StdMath.sol","node_modules/forge-std/src/StdStorage.sol","node_modules/forge-std/src/StdStyle.sol","node_modules/forge-std/src/StdToml.sol","node_modules/forge-std/src/StdUtils.sol","node_modules/forge-std/src/Test.sol","node_modules/forge-std/src/Vm.sol","node_modules/forge-std/src/console.sol","node_modules/forge-std/src/console2.sol","node_modules/forge-std/src/interfaces/IERC165.sol","node_modules/forge-std/src/interfaces/IERC20.sol","node_modules/forge-std/src/interfaces/IERC721.sol","node_modules/forge-std/src/interfaces/IMulticall3.sol","node_modules/forge-std/src/mocks/MockERC20.sol","node_modules/forge-std/src/mocks/MockERC721.sol","node_modules/forge-std/src/safeconsole.sol","src/v1/BybitSafeTrap.sol","src/v1/SafeGuardResponder.sol"],"versionRequirement":"^0.8.20","artifacts":{"BybitSafeTrapTest":{"0.8.33":{"default":{"path":"BybitSafeTrap.t.sol/BybitSafeTrapTest.json","build_id":"0525ed644d1bda42"}}}},"seenByCompiler":true}},"builds":["0525ed644d1bda42","0fe6f21af39541ec","e748f7338fd29765"],"profiles":{"default":{"solc":{"optimizer":{"enabled":true,"runs":200},"metadata":{"useLiteralContent":false,"bytecodeHash":"ipfs","appendCBOR":true},"outputSelection":{"*":{"*":["abi","evm.bytecode.object","evm.bytecode.sourceMap","evm.bytecode.linkReferences","evm.deployedBytecode.object","evm.deployedBytecode.sourceMap","evm.deployedBytecode.linkReferences","evm.deployedBytecode.immutableReferences","evm.methodIdentifiers","metadata"]}},"evmVersion":"prague","viaIR":true,"libraries":{}},"vyper":{"evmVersion":"prague","outputSelection":{"*":{"*":["abi","evm.bytecode","evm.deployedBytecode"]}}}}},"preprocessed":false,"mocks":[]}